<?xml version="1.0" encoding="UTF-8"?>
<xml>
	<uid>O_HERO</uid>
	<object>
		<bbox>1</bbox>
		<width>400</width>
		<height>500</height>
		<x>200</x>
		<y>470</y>
		<maxScale>100</maxScale>
		<clone/>
		<speech>White</speech>
		<title>
			<English>Toi</English>
			<French>Moi</French>
		</title>
		<disabled>0</disabled>
		<palette1>Original</palette1>
		<palette2>Original</palette2>
		<palette3/>
		<palette4/>
		<speedx>200</speedx>
		<speedy>100</speedy>
		<ghost>0</ghost>
		<ghostRate>20</ghostRate>
		<ghostCount>8</ghostCount>
		<turning>1</turning>
		<turningFPS>10</turningFPS>
	</object>
	<anims>
		<STOP fps="12" loopCount="-1" loopRangeMin="0" loopRangeMax="-1" loopRangeCount="0" linkFrame="-1" flip="1" groupType="0">
			<LEFT count="16">
				<frames>
					<frame md5="E8984F67F774C0CF4D662685225A23FE" xtrim="148" ytrim="66" wtrim="108" htrim="414" xdraw="146" ydraw="64" wdraw="112" hdraw="418"/>
					<frame md5="E8984F67F774C0CF4D662685225A23FE" xtrim="148" ytrim="66" wtrim="108" htrim="414" xdraw="146" ydraw="64" wdraw="112" hdraw="418"/>
					<frame md5="E8984F67F774C0CF4D662685225A23FE" xtrim="148" ytrim="66" wtrim="108" htrim="414" xdraw="146" ydraw="64" wdraw="112" hdraw="418"/>
					<frame md5="E8984F67F774C0CF4D662685225A23FE" xtrim="148" ytrim="66" wtrim="108" htrim="414" xdraw="146" ydraw="64" wdraw="112" hdraw="418"/>
					<frame md5="C6F782DA5234A422501E24F1C5DF5262" xtrim="148" ytrim="68" wtrim="108" htrim="412" xdraw="146" ydraw="66" wdraw="112" hdraw="416"/>
					<frame md5="19B6FA7BA52A52F660A6D45F3AFAA82C" xtrim="148" ytrim="68" wtrim="108" htrim="412" xdraw="146" ydraw="66" wdraw="112" hdraw="416"/>
					<frame md5="65B4B43808B804A09C30BE371E94AE3D" xtrim="148" ytrim="68" wtrim="108" htrim="412" xdraw="146" ydraw="66" wdraw="112" hdraw="416"/>
					<frame md5="541EA45E78C0AFE869E758D00CD66BF3" xtrim="148" ytrim="70" wtrim="108" htrim="410" xdraw="146" ydraw="68" wdraw="112" hdraw="414"/>
					<frame md5="399EA4D793DDF5BB04506090CDDB3E69" xtrim="148" ytrim="70" wtrim="108" htrim="410" xdraw="146" ydraw="68" wdraw="112" hdraw="414"/>
					<frame md5="6A120C8B6AC7D1FBB93AB590E6B2A875" xtrim="148" ytrim="72" wtrim="108" htrim="408" xdraw="146" ydraw="70" wdraw="112" hdraw="412"/>
					<frame md5="6A120C8B6AC7D1FBB93AB590E6B2A875" xtrim="148" ytrim="72" wtrim="108" htrim="408" xdraw="146" ydraw="70" wdraw="112" hdraw="412"/>
					<frame md5="399EA4D793DDF5BB04506090CDDB3E69" xtrim="148" ytrim="70" wtrim="108" htrim="410" xdraw="146" ydraw="68" wdraw="112" hdraw="414"/>
					<frame md5="541EA45E78C0AFE869E758D00CD66BF3" xtrim="148" ytrim="70" wtrim="108" htrim="410" xdraw="146" ydraw="68" wdraw="112" hdraw="414"/>
					<frame md5="65B4B43808B804A09C30BE371E94AE3D" xtrim="148" ytrim="68" wtrim="108" htrim="412" xdraw="146" ydraw="66" wdraw="112" hdraw="416"/>
					<frame md5="19B6FA7BA52A52F660A6D45F3AFAA82C" xtrim="148" ytrim="68" wtrim="108" htrim="412" xdraw="146" ydraw="66" wdraw="112" hdraw="416"/>
					<frame md5="C6F782DA5234A422501E24F1C5DF5262" xtrim="148" ytrim="68" wtrim="108" htrim="412" xdraw="146" ydraw="66" wdraw="112" hdraw="416"/>
				</frames>
			</LEFT>
			<RIGHT count="16">
				<frames>
					<frame md5="E8984F67F774C0CF4D662685225A23FE" xtrim="144" ytrim="66" wtrim="108" htrim="414" xdraw="142" ydraw="64" wdraw="112" hdraw="418"/>
					<frame md5="E8984F67F774C0CF4D662685225A23FE" xtrim="144" ytrim="66" wtrim="108" htrim="414" xdraw="142" ydraw="64" wdraw="112" hdraw="418"/>
					<frame md5="E8984F67F774C0CF4D662685225A23FE" xtrim="144" ytrim="66" wtrim="108" htrim="414" xdraw="142" ydraw="64" wdraw="112" hdraw="418"/>
					<frame md5="E8984F67F774C0CF4D662685225A23FE" xtrim="144" ytrim="66" wtrim="108" htrim="414" xdraw="142" ydraw="64" wdraw="112" hdraw="418"/>
					<frame md5="C6F782DA5234A422501E24F1C5DF5262" xtrim="144" ytrim="68" wtrim="108" htrim="412" xdraw="142" ydraw="66" wdraw="112" hdraw="416"/>
					<frame md5="19B6FA7BA52A52F660A6D45F3AFAA82C" xtrim="144" ytrim="68" wtrim="108" htrim="412" xdraw="142" ydraw="66" wdraw="112" hdraw="416"/>
					<frame md5="65B4B43808B804A09C30BE371E94AE3D" xtrim="144" ytrim="68" wtrim="108" htrim="412" xdraw="142" ydraw="66" wdraw="112" hdraw="416"/>
					<frame md5="541EA45E78C0AFE869E758D00CD66BF3" xtrim="144" ytrim="70" wtrim="108" htrim="410" xdraw="142" ydraw="68" wdraw="112" hdraw="414"/>
					<frame md5="399EA4D793DDF5BB04506090CDDB3E69" xtrim="144" ytrim="70" wtrim="108" htrim="410" xdraw="142" ydraw="68" wdraw="112" hdraw="414"/>
					<frame md5="6A120C8B6AC7D1FBB93AB590E6B2A875" xtrim="144" ytrim="72" wtrim="108" htrim="408" xdraw="142" ydraw="70" wdraw="112" hdraw="412"/>
					<frame md5="6A120C8B6AC7D1FBB93AB590E6B2A875" xtrim="144" ytrim="72" wtrim="108" htrim="408" xdraw="142" ydraw="70" wdraw="112" hdraw="412"/>
					<frame md5="399EA4D793DDF5BB04506090CDDB3E69" xtrim="144" ytrim="70" wtrim="108" htrim="410" xdraw="142" ydraw="68" wdraw="112" hdraw="414"/>
					<frame md5="541EA45E78C0AFE869E758D00CD66BF3" xtrim="144" ytrim="70" wtrim="108" htrim="410" xdraw="142" ydraw="68" wdraw="112" hdraw="414"/>
					<frame md5="65B4B43808B804A09C30BE371E94AE3D" xtrim="144" ytrim="68" wtrim="108" htrim="412" xdraw="142" ydraw="66" wdraw="112" hdraw="416"/>
					<frame md5="19B6FA7BA52A52F660A6D45F3AFAA82C" xtrim="144" ytrim="68" wtrim="108" htrim="412" xdraw="142" ydraw="66" wdraw="112" hdraw="416"/>
					<frame md5="C6F782DA5234A422501E24F1C5DF5262" xtrim="144" ytrim="68" wtrim="108" htrim="412" xdraw="142" ydraw="66" wdraw="112" hdraw="416"/>
				</frames>
			</RIGHT>
			<FRONT count="29">
				<frames>
					<frame md5="65A40BA45244A6B64BCA0EF142565367" xtrim="146" ytrim="70" wtrim="100" htrim="420" xdraw="144" ydraw="68" wdraw="104" hdraw="424"/>
					<frame md5="65A40BA45244A6B64BCA0EF142565367" xtrim="146" ytrim="70" wtrim="100" htrim="420" xdraw="144" ydraw="68" wdraw="104" hdraw="424"/>
					<frame md5="887FE0EC6F93C60C7B82B811B15A9765" xtrim="146" ytrim="70" wtrim="100" htrim="420" xdraw="144" ydraw="68" wdraw="104" hdraw="424"/>
					<frame md5="A7FB74BCD3C971C87173B7D444869D1C" xtrim="146" ytrim="72" wtrim="100" htrim="418" xdraw="144" ydraw="70" wdraw="104" hdraw="422"/>
					<frame md5="0D43984F937FDF9CA0666B907996E32B" xtrim="146" ytrim="74" wtrim="100" htrim="416" xdraw="144" ydraw="72" wdraw="104" hdraw="420"/>
					<frame md5="A7FB74BCD3C971C87173B7D444869D1C" xtrim="146" ytrim="72" wtrim="100" htrim="418" xdraw="144" ydraw="70" wdraw="104" hdraw="422"/>
					<frame md5="887FE0EC6F93C60C7B82B811B15A9765" xtrim="146" ytrim="70" wtrim="100" htrim="420" xdraw="144" ydraw="68" wdraw="104" hdraw="424"/>
					<frame md5="65A40BA45244A6B64BCA0EF142565367" xtrim="146" ytrim="70" wtrim="100" htrim="420" xdraw="144" ydraw="68" wdraw="104" hdraw="424"/>
					<frame md5="65A40BA45244A6B64BCA0EF142565367" xtrim="146" ytrim="70" wtrim="100" htrim="420" xdraw="144" ydraw="68" wdraw="104" hdraw="424"/>
					<frame md5="65A40BA45244A6B64BCA0EF142565367" xtrim="146" ytrim="70" wtrim="100" htrim="420" xdraw="144" ydraw="68" wdraw="104" hdraw="424"/>
					<frame md5="3FE336A029CF8DC9FA8FF0F2839513BE" xtrim="146" ytrim="70" wtrim="100" htrim="420" xdraw="144" ydraw="68" wdraw="104" hdraw="424"/>
					<frame md5="6ED1585D79944D93F52207FC26F201B9" xtrim="146" ytrim="72" wtrim="100" htrim="418" xdraw="144" ydraw="70" wdraw="104" hdraw="422"/>
					<frame md5="3FE336A029CF8DC9FA8FF0F2839513BE" xtrim="146" ytrim="70" wtrim="100" htrim="420" xdraw="144" ydraw="68" wdraw="104" hdraw="424"/>
					<frame md5="65A40BA45244A6B64BCA0EF142565367" xtrim="146" ytrim="70" wtrim="100" htrim="420" xdraw="144" ydraw="68" wdraw="104" hdraw="424"/>
					<frame md5="65A40BA45244A6B64BCA0EF142565367" xtrim="146" ytrim="70" wtrim="100" htrim="420" xdraw="144" ydraw="68" wdraw="104" hdraw="424"/>
					<frame md5="65A40BA45244A6B64BCA0EF142565367" xtrim="146" ytrim="70" wtrim="100" htrim="420" xdraw="144" ydraw="68" wdraw="104" hdraw="424"/>
					<frame md5="65A40BA45244A6B64BCA0EF142565367" xtrim="146" ytrim="70" wtrim="100" htrim="420" xdraw="144" ydraw="68" wdraw="104" hdraw="424"/>
					<frame md5="7CB9514C1DF4CA8318B978431FC4ADD1" xtrim="146" ytrim="70" wtrim="100" htrim="420" xdraw="144" ydraw="68" wdraw="104" hdraw="424"/>
					<frame md5="84ECEEC5029381A92C48626A52294EF9" xtrim="146" ytrim="72" wtrim="100" htrim="418" xdraw="144" ydraw="70" wdraw="104" hdraw="422"/>
					<frame md5="58DE294CDB3D82A377D49F9FCF81FC6B" xtrim="146" ytrim="74" wtrim="100" htrim="416" xdraw="144" ydraw="72" wdraw="104" hdraw="420"/>
					<frame md5="E14599C83C7AED60AC5D82A46D888171" xtrim="146" ytrim="76" wtrim="100" htrim="414" xdraw="144" ydraw="74" wdraw="104" hdraw="418"/>
					<frame md5="8F14CDDAC2D83A181A35DE226118CD03" xtrim="146" ytrim="76" wtrim="100" htrim="414" xdraw="144" ydraw="74" wdraw="104" hdraw="418"/>
					<frame md5="E14599C83C7AED60AC5D82A46D888171" xtrim="146" ytrim="76" wtrim="100" htrim="414" xdraw="144" ydraw="74" wdraw="104" hdraw="418"/>
					<frame md5="58DE294CDB3D82A377D49F9FCF81FC6B" xtrim="146" ytrim="74" wtrim="100" htrim="416" xdraw="144" ydraw="72" wdraw="104" hdraw="420"/>
					<frame md5="8F14CDDAC2D83A181A35DE226118CD03" xtrim="146" ytrim="76" wtrim="100" htrim="414" xdraw="144" ydraw="74" wdraw="104" hdraw="418"/>
					<frame md5="E14599C83C7AED60AC5D82A46D888171" xtrim="146" ytrim="76" wtrim="100" htrim="414" xdraw="144" ydraw="74" wdraw="104" hdraw="418"/>
					<frame md5="58DE294CDB3D82A377D49F9FCF81FC6B" xtrim="146" ytrim="74" wtrim="100" htrim="416" xdraw="144" ydraw="72" wdraw="104" hdraw="420"/>
					<frame md5="84ECEEC5029381A92C48626A52294EF9" xtrim="146" ytrim="72" wtrim="100" htrim="418" xdraw="144" ydraw="70" wdraw="104" hdraw="422"/>
					<frame md5="7CB9514C1DF4CA8318B978431FC4ADD1" xtrim="146" ytrim="70" wtrim="100" htrim="420" xdraw="144" ydraw="68" wdraw="104" hdraw="424"/>
				</frames>
			</FRONT>
			<BACK count="15">
				<frames>
					<frame md5="233A324950560CC83EC55281F80F2E3B" xtrim="150" ytrim="72" wtrim="96" htrim="396" xdraw="148" ydraw="70" wdraw="100" hdraw="400"/>
					<frame md5="233A324950560CC83EC55281F80F2E3B" xtrim="150" ytrim="72" wtrim="96" htrim="396" xdraw="148" ydraw="70" wdraw="100" hdraw="400"/>
					<frame md5="233A324950560CC83EC55281F80F2E3B" xtrim="150" ytrim="72" wtrim="96" htrim="396" xdraw="148" ydraw="70" wdraw="100" hdraw="400"/>
					<frame md5="233A324950560CC83EC55281F80F2E3B" xtrim="150" ytrim="72" wtrim="96" htrim="396" xdraw="148" ydraw="70" wdraw="100" hdraw="400"/>
					<frame md5="2F7F17DCAD481E7F2570B31D19CBE489" xtrim="150" ytrim="72" wtrim="96" htrim="396" xdraw="148" ydraw="70" wdraw="100" hdraw="400"/>
					<frame md5="F947CD0AF30B56DF5B605302487B47F5" xtrim="150" ytrim="74" wtrim="96" htrim="394" xdraw="148" ydraw="72" wdraw="100" hdraw="398"/>
					<frame md5="7ACAA534B25972B5F13A4EC32ACBAEE8" xtrim="150" ytrim="74" wtrim="94" htrim="394" xdraw="148" ydraw="72" wdraw="98" hdraw="398"/>
					<frame md5="768E62EB10C2090F08AAC27BB04FCADA" xtrim="150" ytrim="74" wtrim="94" htrim="394" xdraw="148" ydraw="72" wdraw="98" hdraw="398"/>
					<frame md5="E06C69BEC4BA55B810CCB48F74A92061" xtrim="150" ytrim="74" wtrim="94" htrim="394" xdraw="148" ydraw="72" wdraw="98" hdraw="398"/>
					<frame md5="E06C69BEC4BA55B810CCB48F74A92061" xtrim="150" ytrim="74" wtrim="94" htrim="394" xdraw="148" ydraw="72" wdraw="98" hdraw="398"/>
					<frame md5="E06C69BEC4BA55B810CCB48F74A92061" xtrim="150" ytrim="74" wtrim="94" htrim="394" xdraw="148" ydraw="72" wdraw="98" hdraw="398"/>
					<frame md5="768E62EB10C2090F08AAC27BB04FCADA" xtrim="150" ytrim="74" wtrim="94" htrim="394" xdraw="148" ydraw="72" wdraw="98" hdraw="398"/>
					<frame md5="7ACAA534B25972B5F13A4EC32ACBAEE8" xtrim="150" ytrim="74" wtrim="94" htrim="394" xdraw="148" ydraw="72" wdraw="98" hdraw="398"/>
					<frame md5="F947CD0AF30B56DF5B605302487B47F5" xtrim="150" ytrim="74" wtrim="96" htrim="394" xdraw="148" ydraw="72" wdraw="100" hdraw="398"/>
					<frame md5="2F7F17DCAD481E7F2570B31D19CBE489" xtrim="150" ytrim="72" wtrim="96" htrim="396" xdraw="148" ydraw="70" wdraw="100" hdraw="400"/>
				</frames>
			</BACK>
		</STOP>
		<WALK fps="12" loopCount="-1" loopRangeMin="0" loopRangeMax="-1" loopRangeCount="0" linkFrame="-1" flip="1" groupType="0">
			<LEFT count="10">
				<frames>
					<frame md5="7369181DAC137F4258E48E886968D3BC" xtrim="62" ytrim="72" wtrim="232" htrim="414" xdraw="60" ydraw="70" wdraw="236" hdraw="418"/>
					<frame md5="4E1ACBE3AF2444C02F039CA61F497882" xtrim="90" ytrim="68" wtrim="184" htrim="418" xdraw="88" ydraw="66" wdraw="188" hdraw="422"/>
					<frame md5="80E822A621DCCB696810F9C6814A7288" xtrim="152" ytrim="60" wtrim="112" htrim="422" xdraw="150" ydraw="58" wdraw="116" hdraw="426"/>
					<frame md5="76EAD25AE5CE054FB536F21C1E425D9A" xtrim="140" ytrim="66" wtrim="118" htrim="416" xdraw="138" ydraw="64" wdraw="122" hdraw="420"/>
					<frame md5="578BAC9BC1E68A2EFEC4038FD17EE97A" xtrim="86" ytrim="74" wtrim="170" htrim="408" xdraw="84" ydraw="72" wdraw="174" hdraw="412"/>
					<frame md5="2496431F952A5B2DFE664DB56B785AA7" xtrim="58" ytrim="74" wtrim="244" htrim="410" xdraw="56" ydraw="72" wdraw="248" hdraw="414"/>
					<frame md5="92116175EDF2BEDD2C0012EF68413FAA" xtrim="104" ytrim="68" wtrim="196" htrim="412" xdraw="102" ydraw="66" wdraw="200" hdraw="416"/>
					<frame md5="04CACAC1C1AEFE33DC4729163C57BE6F" xtrim="148" ytrim="58" wtrim="140" htrim="424" xdraw="146" ydraw="56" wdraw="144" hdraw="428"/>
					<frame md5="55D2336F4769DF69DE6F7522CF2AECB0" xtrim="142" ytrim="64" wtrim="120" htrim="418" xdraw="140" ydraw="62" wdraw="124" hdraw="422"/>
					<frame md5="0C4D36CA373192321FB1A2259BD6DCA4" xtrim="72" ytrim="74" wtrim="192" htrim="406" xdraw="70" ydraw="72" wdraw="196" hdraw="410"/>
				</frames>
			</LEFT>
			<RIGHT count="10">
				<frames>
					<frame md5="7369181DAC137F4258E48E886968D3BC" xtrim="106" ytrim="72" wtrim="232" htrim="414" xdraw="104" ydraw="70" wdraw="236" hdraw="418"/>
					<frame md5="4E1ACBE3AF2444C02F039CA61F497882" xtrim="126" ytrim="68" wtrim="184" htrim="418" xdraw="124" ydraw="66" wdraw="188" hdraw="422"/>
					<frame md5="80E822A621DCCB696810F9C6814A7288" xtrim="136" ytrim="60" wtrim="112" htrim="422" xdraw="134" ydraw="58" wdraw="116" hdraw="426"/>
					<frame md5="76EAD25AE5CE054FB536F21C1E425D9A" xtrim="142" ytrim="66" wtrim="118" htrim="416" xdraw="140" ydraw="64" wdraw="122" hdraw="420"/>
					<frame md5="578BAC9BC1E68A2EFEC4038FD17EE97A" xtrim="144" ytrim="74" wtrim="170" htrim="408" xdraw="142" ydraw="72" wdraw="174" hdraw="412"/>
					<frame md5="2496431F952A5B2DFE664DB56B785AA7" xtrim="98" ytrim="74" wtrim="244" htrim="410" xdraw="96" ydraw="72" wdraw="248" hdraw="414"/>
					<frame md5="92116175EDF2BEDD2C0012EF68413FAA" xtrim="100" ytrim="68" wtrim="196" htrim="412" xdraw="98" ydraw="66" wdraw="200" hdraw="416"/>
					<frame md5="04CACAC1C1AEFE33DC4729163C57BE6F" xtrim="112" ytrim="58" wtrim="140" htrim="424" xdraw="110" ydraw="56" wdraw="144" hdraw="428"/>
					<frame md5="55D2336F4769DF69DE6F7522CF2AECB0" xtrim="138" ytrim="64" wtrim="120" htrim="418" xdraw="136" ydraw="62" wdraw="124" hdraw="422"/>
					<frame md5="0C4D36CA373192321FB1A2259BD6DCA4" xtrim="136" ytrim="74" wtrim="192" htrim="406" xdraw="134" ydraw="72" wdraw="196" hdraw="410"/>
				</frames>
			</RIGHT>
			<FRONT count="7">
				<frames>
					<frame md5="33335A225EACF8B796857AE8DD4BCF84" xtrim="144" ytrim="46" wtrim="102" htrim="426" xdraw="142" ydraw="44" wdraw="106" hdraw="430"/>
					<frame md5="C909C75CCF6CE719DEC3F83383BB60CD" xtrim="146" ytrim="52" wtrim="98" htrim="422" xdraw="144" ydraw="50" wdraw="102" hdraw="426"/>
					<frame md5="01B3B74049F9DA1501D6716C7F23506B" xtrim="146" ytrim="50" wtrim="100" htrim="422" xdraw="144" ydraw="48" wdraw="104" hdraw="426"/>
					<frame md5="E3C14DA41C5FC839D2C59553E319A8AB" xtrim="144" ytrim="50" wtrim="102" htrim="416" xdraw="142" ydraw="48" wdraw="106" hdraw="420"/>
					<frame md5="97C33232BCBBF6B4831345F90F8A02D1" xtrim="146" ytrim="48" wtrim="98" htrim="452" xdraw="144" ydraw="46" wdraw="102" hdraw="456"/>
					<frame md5="0E92E353E258B35499A6F9C4AE34BFB8" xtrim="146" ytrim="50" wtrim="102" htrim="444" xdraw="144" ydraw="48" wdraw="106" hdraw="448"/>
					<frame md5="FEEA01064A1A3CEAFA1CEC1C03A7CBFF" xtrim="146" ytrim="52" wtrim="98" htrim="430" xdraw="144" ydraw="50" wdraw="102" hdraw="434"/>
				</frames>
			</FRONT>
			<BACK count="7">
				<frames>
					<frame md5="AA6DA4C23D8289097452269A03C8C4F0" xtrim="146" ytrim="50" wtrim="104" htrim="432" xdraw="144" ydraw="48" wdraw="108" hdraw="436"/>
					<frame md5="C889D08AA88FABC885F000F25B31E8C0" xtrim="146" ytrim="56" wtrim="106" htrim="430" xdraw="144" ydraw="54" wdraw="110" hdraw="434"/>
					<frame md5="31BE08579096593F112570D20112A5F8" xtrim="146" ytrim="58" wtrim="104" htrim="426" xdraw="144" ydraw="56" wdraw="108" hdraw="430"/>
					<frame md5="C38E28DDA5A0546ECE9FDD48314FD425" xtrim="144" ytrim="56" wtrim="106" htrim="412" xdraw="142" ydraw="54" wdraw="110" hdraw="416"/>
					<frame md5="8A8301289E188638D091508C4A617AA6" xtrim="144" ytrim="48" wtrim="106" htrim="436" xdraw="142" ydraw="46" wdraw="110" hdraw="440"/>
					<frame md5="A44AC194EF788C6FF2DA9AB9D2CA8727" xtrim="146" ytrim="56" wtrim="106" htrim="432" xdraw="144" ydraw="54" wdraw="110" hdraw="436"/>
					<frame md5="04F57AADECAA1A6F2BCCCCF19483DF5E" xtrim="146" ytrim="54" wtrim="102" htrim="416" xdraw="144" ydraw="52" wdraw="106" hdraw="420"/>
				</frames>
			</BACK>
		</WALK>
		<TAKE fps="6" loopCount="0" loopRangeMin="0" loopRangeMax="-1" loopRangeCount="0" linkFrame="-1" flip="1" groupType="0">
			<LEFT count="17">
				<frames>
					<frame md5="F1F29FA26691696E8636A603919817AE" xtrim="164" ytrim="36" wtrim="102" htrim="432" xdraw="162" ydraw="34" wdraw="106" hdraw="436"/>
					<frame md5="010245C10FF0750B42AD2886822095C0" xtrim="76" ytrim="68" wtrim="146" htrim="398" xdraw="74" ydraw="66" wdraw="150" hdraw="402"/>
					<frame md5="840E4C35AF16E49D5B96BD0D673A90AA" xtrim="52" ytrim="98" wtrim="170" htrim="368" xdraw="50" ydraw="96" wdraw="174" hdraw="372"/>
					<frame md5="DD4C620389479A89DABAA4921CC20442" xtrim="48" ytrim="200" wtrim="170" htrim="266" xdraw="46" ydraw="198" wdraw="174" hdraw="270"/>
					<frame md5="8F2B3F690FBD6660FCE050067A7DDA73" xtrim="10" ytrim="234" wtrim="208" htrim="232" xdraw="8" ydraw="232" wdraw="212" hdraw="236"/>
					<frame md5="FB3C4A7682E5B4F310838BD3B96FB0F1" xtrim="8" ytrim="234" wtrim="210" htrim="230" xdraw="6" ydraw="232" wdraw="214" hdraw="234"/>
					<frame md5="E4E7572AAB330280EF9585F8651F5043" xtrim="8" ytrim="234" wtrim="208" htrim="230" xdraw="6" ydraw="232" wdraw="212" hdraw="234"/>
					<frame md5="EFB4D169FAAB3B01923C67C99611F0F7" xtrim="30" ytrim="214" wtrim="186" htrim="250" xdraw="28" ydraw="212" wdraw="190" hdraw="254"/>
					<frame md5="A6292298B32053F0FEC419FC480153CC" xtrim="88" ytrim="140" wtrim="130" htrim="328" xdraw="86" ydraw="138" wdraw="134" hdraw="332"/>
					<frame md5="6F60A2B2D7B7B243090CBCCDBF5026F4" xtrim="122" ytrim="74" wtrim="106" htrim="392" xdraw="120" ydraw="72" wdraw="110" hdraw="396"/>
					<frame md5="F342B1A352599FFC29CDEBD70299F0C6" xtrim="150" ytrim="36" wtrim="114" htrim="432" xdraw="148" ydraw="34" wdraw="118" hdraw="436"/>
					<frame md5="1AB5DB7D358A22EBA393B8047C16B621" xtrim="150" ytrim="34" wtrim="114" htrim="434" xdraw="148" ydraw="32" wdraw="118" hdraw="438"/>
					<frame md5="D4E76F1EE6DE7756C766AB5C199613B3" xtrim="152" ytrim="34" wtrim="112" htrim="434" xdraw="150" ydraw="32" wdraw="116" hdraw="438"/>
					<frame md5="708B19B82675CE175696AD338D670501" xtrim="152" ytrim="34" wtrim="112" htrim="434" xdraw="150" ydraw="32" wdraw="116" hdraw="438"/>
					<frame md5="4C90972FD807A7C7E9EE8083D5CD8677" xtrim="164" ytrim="36" wtrim="100" htrim="432" xdraw="162" ydraw="34" wdraw="104" hdraw="436"/>
					<frame md5="99EE6A9C151CDDDB444065165BDA801B" xtrim="164" ytrim="34" wtrim="102" htrim="432" xdraw="162" ydraw="32" wdraw="106" hdraw="436"/>
					<frame md5="0726390578CFA4AFCF946A2A2315C618" xtrim="152" ytrim="34" wtrim="114" htrim="434" xdraw="150" ydraw="32" wdraw="118" hdraw="438"/>
				</frames>
			</LEFT>
			<RIGHT count="17">
				<frames>
					<frame md5="F1F29FA26691696E8636A603919817AE" xtrim="134" ytrim="36" wtrim="102" htrim="432" xdraw="132" ydraw="34" wdraw="106" hdraw="436"/>
					<frame md5="010245C10FF0750B42AD2886822095C0" xtrim="178" ytrim="68" wtrim="146" htrim="398" xdraw="176" ydraw="66" wdraw="150" hdraw="402"/>
					<frame md5="840E4C35AF16E49D5B96BD0D673A90AA" xtrim="178" ytrim="98" wtrim="170" htrim="368" xdraw="176" ydraw="96" wdraw="174" hdraw="372"/>
					<frame md5="DD4C620389479A89DABAA4921CC20442" xtrim="182" ytrim="200" wtrim="170" htrim="266" xdraw="180" ydraw="198" wdraw="174" hdraw="270"/>
					<frame md5="8F2B3F690FBD6660FCE050067A7DDA73" xtrim="182" ytrim="234" wtrim="208" htrim="232" xdraw="180" ydraw="232" wdraw="212" hdraw="236"/>
					<frame md5="FB3C4A7682E5B4F310838BD3B96FB0F1" xtrim="182" ytrim="234" wtrim="210" htrim="230" xdraw="180" ydraw="232" wdraw="214" hdraw="234"/>
					<frame md5="E4E7572AAB330280EF9585F8651F5043" xtrim="184" ytrim="234" wtrim="208" htrim="230" xdraw="182" ydraw="232" wdraw="212" hdraw="234"/>
					<frame md5="EFB4D169FAAB3B01923C67C99611F0F7" xtrim="184" ytrim="214" wtrim="186" htrim="250" xdraw="182" ydraw="212" wdraw="190" hdraw="254"/>
					<frame md5="A6292298B32053F0FEC419FC480153CC" xtrim="182" ytrim="140" wtrim="130" htrim="328" xdraw="180" ydraw="138" wdraw="134" hdraw="332"/>
					<frame md5="6F60A2B2D7B7B243090CBCCDBF5026F4" xtrim="172" ytrim="74" wtrim="106" htrim="392" xdraw="170" ydraw="72" wdraw="110" hdraw="396"/>
					<frame md5="F342B1A352599FFC29CDEBD70299F0C6" xtrim="136" ytrim="36" wtrim="114" htrim="432" xdraw="134" ydraw="34" wdraw="118" hdraw="436"/>
					<frame md5="1AB5DB7D358A22EBA393B8047C16B621" xtrim="136" ytrim="34" wtrim="114" htrim="434" xdraw="134" ydraw="32" wdraw="118" hdraw="438"/>
					<frame md5="D4E76F1EE6DE7756C766AB5C199613B3" xtrim="136" ytrim="34" wtrim="112" htrim="434" xdraw="134" ydraw="32" wdraw="116" hdraw="438"/>
					<frame md5="708B19B82675CE175696AD338D670501" xtrim="136" ytrim="34" wtrim="112" htrim="434" xdraw="134" ydraw="32" wdraw="116" hdraw="438"/>
					<frame md5="4C90972FD807A7C7E9EE8083D5CD8677" xtrim="136" ytrim="36" wtrim="100" htrim="432" xdraw="134" ydraw="34" wdraw="104" hdraw="436"/>
					<frame md5="99EE6A9C151CDDDB444065165BDA801B" xtrim="134" ytrim="34" wtrim="102" htrim="432" xdraw="132" ydraw="32" wdraw="106" hdraw="436"/>
					<frame md5="0726390578CFA4AFCF946A2A2315C618" xtrim="134" ytrim="34" wtrim="114" htrim="434" xdraw="132" ydraw="32" wdraw="118" hdraw="438"/>
				</frames>
			</RIGHT>
			<FRONT>
				<frames/>
			</FRONT>
			<BACK>
				<frames/>
			</BACK>
		</TAKE>
		<TALK fps="12" loopCount="-1" loopRangeMin="0" loopRangeMax="-1" loopRangeCount="0" linkFrame="-1" flip="1" groupType="0">
			<LEFT count="16">
				<frames>
					<frame md5="E8984F67F774C0CF4D662685225A23FE" xtrim="148" ytrim="66" wtrim="108" htrim="414" xdraw="146" ydraw="64" wdraw="112" hdraw="418"/>
					<frame md5="0F8A85BF7A91C13768BE6067D1508579" xtrim="148" ytrim="66" wtrim="108" htrim="414" xdraw="146" ydraw="64" wdraw="112" hdraw="418"/>
					<frame md5="9986CA541890C490D4F89E825BD3E45D" xtrim="148" ytrim="66" wtrim="108" htrim="414" xdraw="146" ydraw="64" wdraw="112" hdraw="418"/>
					<frame md5="E8984F67F774C0CF4D662685225A23FE" xtrim="148" ytrim="66" wtrim="108" htrim="414" xdraw="146" ydraw="64" wdraw="112" hdraw="418"/>
					<frame md5="E8984F67F774C0CF4D662685225A23FE" xtrim="148" ytrim="66" wtrim="108" htrim="414" xdraw="146" ydraw="64" wdraw="112" hdraw="418"/>
					<frame md5="F6CEFC584B248BB6C471AA9DF60A0D78" xtrim="148" ytrim="68" wtrim="108" htrim="412" xdraw="146" ydraw="66" wdraw="112" hdraw="416"/>
					<frame md5="A9DF002A192FC2EED213012220F8322E" xtrim="148" ytrim="68" wtrim="108" htrim="412" xdraw="146" ydraw="66" wdraw="112" hdraw="416"/>
					<frame md5="65B4B43808B804A09C30BE371E94AE3D" xtrim="148" ytrim="68" wtrim="108" htrim="412" xdraw="146" ydraw="66" wdraw="112" hdraw="416"/>
					<frame md5="E45ADF65BD2FA59675167704C5DCEF0D" xtrim="148" ytrim="70" wtrim="108" htrim="410" xdraw="146" ydraw="68" wdraw="112" hdraw="414"/>
					<frame md5="399EA4D793DDF5BB04506090CDDB3E69" xtrim="148" ytrim="70" wtrim="108" htrim="410" xdraw="146" ydraw="68" wdraw="112" hdraw="414"/>
					<frame md5="6A120C8B6AC7D1FBB93AB590E6B2A875" xtrim="148" ytrim="72" wtrim="108" htrim="408" xdraw="146" ydraw="70" wdraw="112" hdraw="412"/>
					<frame md5="399EA4D793DDF5BB04506090CDDB3E69" xtrim="148" ytrim="70" wtrim="108" htrim="410" xdraw="146" ydraw="68" wdraw="112" hdraw="414"/>
					<frame md5="541EA45E78C0AFE869E758D00CD66BF3" xtrim="148" ytrim="70" wtrim="108" htrim="410" xdraw="146" ydraw="68" wdraw="112" hdraw="414"/>
					<frame md5="99AB709A843B1252B781E0101B2B385D" xtrim="148" ytrim="68" wtrim="108" htrim="412" xdraw="146" ydraw="66" wdraw="112" hdraw="416"/>
					<frame md5="A7CA75E3DD85AACFAF8647EF5FD0025C" xtrim="148" ytrim="68" wtrim="108" htrim="412" xdraw="146" ydraw="66" wdraw="112" hdraw="416"/>
					<frame md5="C6F782DA5234A422501E24F1C5DF5262" xtrim="148" ytrim="68" wtrim="108" htrim="412" xdraw="146" ydraw="66" wdraw="112" hdraw="416"/>
				</frames>
			</LEFT>
			<RIGHT count="16">
				<frames>
					<frame md5="E8984F67F774C0CF4D662685225A23FE" xtrim="144" ytrim="66" wtrim="108" htrim="414" xdraw="142" ydraw="64" wdraw="112" hdraw="418"/>
					<frame md5="0F8A85BF7A91C13768BE6067D1508579" xtrim="144" ytrim="66" wtrim="108" htrim="414" xdraw="142" ydraw="64" wdraw="112" hdraw="418"/>
					<frame md5="9986CA541890C490D4F89E825BD3E45D" xtrim="144" ytrim="66" wtrim="108" htrim="414" xdraw="142" ydraw="64" wdraw="112" hdraw="418"/>
					<frame md5="E8984F67F774C0CF4D662685225A23FE" xtrim="144" ytrim="66" wtrim="108" htrim="414" xdraw="142" ydraw="64" wdraw="112" hdraw="418"/>
					<frame md5="E8984F67F774C0CF4D662685225A23FE" xtrim="144" ytrim="66" wtrim="108" htrim="414" xdraw="142" ydraw="64" wdraw="112" hdraw="418"/>
					<frame md5="F6CEFC584B248BB6C471AA9DF60A0D78" xtrim="144" ytrim="68" wtrim="108" htrim="412" xdraw="142" ydraw="66" wdraw="112" hdraw="416"/>
					<frame md5="A9DF002A192FC2EED213012220F8322E" xtrim="144" ytrim="68" wtrim="108" htrim="412" xdraw="142" ydraw="66" wdraw="112" hdraw="416"/>
					<frame md5="65B4B43808B804A09C30BE371E94AE3D" xtrim="144" ytrim="68" wtrim="108" htrim="412" xdraw="142" ydraw="66" wdraw="112" hdraw="416"/>
					<frame md5="E45ADF65BD2FA59675167704C5DCEF0D" xtrim="144" ytrim="70" wtrim="108" htrim="410" xdraw="142" ydraw="68" wdraw="112" hdraw="414"/>
					<frame md5="399EA4D793DDF5BB04506090CDDB3E69" xtrim="144" ytrim="70" wtrim="108" htrim="410" xdraw="142" ydraw="68" wdraw="112" hdraw="414"/>
					<frame md5="6A120C8B6AC7D1FBB93AB590E6B2A875" xtrim="144" ytrim="72" wtrim="108" htrim="408" xdraw="142" ydraw="70" wdraw="112" hdraw="412"/>
					<frame md5="399EA4D793DDF5BB04506090CDDB3E69" xtrim="144" ytrim="70" wtrim="108" htrim="410" xdraw="142" ydraw="68" wdraw="112" hdraw="414"/>
					<frame md5="541EA45E78C0AFE869E758D00CD66BF3" xtrim="144" ytrim="70" wtrim="108" htrim="410" xdraw="142" ydraw="68" wdraw="112" hdraw="414"/>
					<frame md5="99AB709A843B1252B781E0101B2B385D" xtrim="144" ytrim="68" wtrim="108" htrim="412" xdraw="142" ydraw="66" wdraw="112" hdraw="416"/>
					<frame md5="A7CA75E3DD85AACFAF8647EF5FD0025C" xtrim="144" ytrim="68" wtrim="108" htrim="412" xdraw="142" ydraw="66" wdraw="112" hdraw="416"/>
					<frame md5="C6F782DA5234A422501E24F1C5DF5262" xtrim="144" ytrim="68" wtrim="108" htrim="412" xdraw="142" ydraw="66" wdraw="112" hdraw="416"/>
				</frames>
			</RIGHT>
			<FRONT>
				<frames/>
			</FRONT>
			<BACK>
				<frames/>
			</BACK>
		</TALK>
		<SURPRISED_TALK fps="6" loopCount="0" loopRangeMin="0" loopRangeMax="-1" loopRangeCount="0" linkFrame="-1" flip="1" groupType="0">
			<LEFT count="41">
				<frames>
					<frame md5="8D13EDA71E49F59240C31A0E0838BC76" xtrim="148" ytrim="68" wtrim="108" htrim="412" xdraw="146" ydraw="66" wdraw="112" hdraw="416"/>
					<frame md5="27EF89757E8369808FDEE1260802EEBE" xtrim="148" ytrim="68" wtrim="104" htrim="412" xdraw="146" ydraw="66" wdraw="108" hdraw="416"/>
					<frame md5="05A81CE86725698D5D6B6AB9C8173E2F" xtrim="130" ytrim="68" wtrim="138" htrim="412" xdraw="128" ydraw="66" wdraw="142" hdraw="416"/>
					<frame md5="16B9EF650F4866408E77B7C15CE88B32" xtrim="110" ytrim="68" wtrim="186" htrim="412" xdraw="108" ydraw="66" wdraw="190" hdraw="416"/>
					<frame md5="D6BB796C887A55C361AC4E5663671473" xtrim="110" ytrim="68" wtrim="186" htrim="412" xdraw="108" ydraw="66" wdraw="190" hdraw="416"/>
					<frame md5="D6448E7575766FF9E3C3DB6A886ADF95" xtrim="110" ytrim="68" wtrim="186" htrim="412" xdraw="108" ydraw="66" wdraw="190" hdraw="416"/>
					<frame md5="526EA2BF7C5DB26D9F0E1D01C8C2A6C6" xtrim="110" ytrim="68" wtrim="186" htrim="412" xdraw="108" ydraw="66" wdraw="190" hdraw="416"/>
					<frame md5="D6BB796C887A55C361AC4E5663671473" xtrim="110" ytrim="68" wtrim="186" htrim="412" xdraw="108" ydraw="66" wdraw="190" hdraw="416"/>
					<frame md5="D6448E7575766FF9E3C3DB6A886ADF95" xtrim="110" ytrim="68" wtrim="186" htrim="412" xdraw="108" ydraw="66" wdraw="190" hdraw="416"/>
					<frame md5="D6BB796C887A55C361AC4E5663671473" xtrim="110" ytrim="68" wtrim="186" htrim="412" xdraw="108" ydraw="66" wdraw="190" hdraw="416"/>
					<frame md5="D6448E7575766FF9E3C3DB6A886ADF95" xtrim="110" ytrim="68" wtrim="186" htrim="412" xdraw="108" ydraw="66" wdraw="190" hdraw="416"/>
					<frame md5="05A81CE86725698D5D6B6AB9C8173E2F" xtrim="130" ytrim="68" wtrim="138" htrim="412" xdraw="128" ydraw="66" wdraw="142" hdraw="416"/>
					<frame md5="27EF89757E8369808FDEE1260802EEBE" xtrim="148" ytrim="68" wtrim="104" htrim="412" xdraw="146" ydraw="66" wdraw="108" hdraw="416"/>
					<frame md5="8D13EDA71E49F59240C31A0E0838BC76" xtrim="148" ytrim="68" wtrim="108" htrim="412" xdraw="146" ydraw="66" wdraw="112" hdraw="416"/>
					<frame md5="D51B073A4DEC710F04DA07E684DB5008" xtrim="148" ytrim="68" wtrim="108" htrim="412" xdraw="146" ydraw="66" wdraw="112" hdraw="416"/>
					<frame md5="8728AC82DE4B05729B0F3A242FC1AAB7" xtrim="148" ytrim="68" wtrim="108" htrim="412" xdraw="146" ydraw="66" wdraw="112" hdraw="416"/>
					<frame md5="8D13EDA71E49F59240C31A0E0838BC76" xtrim="148" ytrim="68" wtrim="108" htrim="412" xdraw="146" ydraw="66" wdraw="112" hdraw="416"/>
					<frame md5="4E5090D9B00447BF219991212FDF3980" xtrim="148" ytrim="68" wtrim="108" htrim="412" xdraw="146" ydraw="66" wdraw="112" hdraw="416"/>
					<frame md5="8D13EDA71E49F59240C31A0E0838BC76" xtrim="148" ytrim="68" wtrim="108" htrim="412" xdraw="146" ydraw="66" wdraw="112" hdraw="416"/>
					<frame md5="AD016F2A30E2A6898867BA65AF14D70B" xtrim="148" ytrim="68" wtrim="108" htrim="412" xdraw="146" ydraw="66" wdraw="112" hdraw="416"/>
					<frame md5="CA4D48A8525FE03B59ED27BF23ACCCEF" xtrim="148" ytrim="68" wtrim="108" htrim="412" xdraw="146" ydraw="66" wdraw="112" hdraw="416"/>
					<frame md5="AD016F2A30E2A6898867BA65AF14D70B" xtrim="148" ytrim="68" wtrim="108" htrim="412" xdraw="146" ydraw="66" wdraw="112" hdraw="416"/>
					<frame md5="8D13EDA71E49F59240C31A0E0838BC76" xtrim="148" ytrim="68" wtrim="108" htrim="412" xdraw="146" ydraw="66" wdraw="112" hdraw="416"/>
					<frame md5="6964CA9E4B4023D047D8258BF5FA4ABA" xtrim="148" ytrim="68" wtrim="108" htrim="412" xdraw="146" ydraw="66" wdraw="112" hdraw="416"/>
					<frame md5="F6DDD181A8883F48138DDEB471D0DCA5" xtrim="148" ytrim="68" wtrim="108" htrim="412" xdraw="146" ydraw="66" wdraw="112" hdraw="416"/>
					<frame md5="6A743A8A8384A1444B0C04D22607A1DC" xtrim="148" ytrim="68" wtrim="108" htrim="412" xdraw="146" ydraw="66" wdraw="112" hdraw="416"/>
					<frame md5="6A743A8A8384A1444B0C04D22607A1DC" xtrim="148" ytrim="68" wtrim="108" htrim="412" xdraw="146" ydraw="66" wdraw="112" hdraw="416"/>
					<frame md5="8F84193FC320BBE439F1690D2CBF5809" xtrim="148" ytrim="68" wtrim="108" htrim="412" xdraw="146" ydraw="66" wdraw="112" hdraw="416"/>
					<frame md5="4AC24399222983A54D5D1F2282CC79D1" xtrim="148" ytrim="68" wtrim="108" htrim="412" xdraw="146" ydraw="66" wdraw="112" hdraw="416"/>
					<frame md5="61E7EA63A035B60DA374E292F3FF1581" xtrim="148" ytrim="68" wtrim="108" htrim="412" xdraw="146" ydraw="66" wdraw="112" hdraw="416"/>
					<frame md5="5A20DD39F9E83683FC4CDD5179C72B04" xtrim="148" ytrim="68" wtrim="108" htrim="412" xdraw="146" ydraw="66" wdraw="112" hdraw="416"/>
					<frame md5="6E7B2091366501DE3EFE8097BFF64A38" xtrim="148" ytrim="68" wtrim="108" htrim="412" xdraw="146" ydraw="66" wdraw="112" hdraw="416"/>
					<frame md5="F6DDD181A8883F48138DDEB471D0DCA5" xtrim="148" ytrim="68" wtrim="108" htrim="412" xdraw="146" ydraw="66" wdraw="112" hdraw="416"/>
					<frame md5="6964CA9E4B4023D047D8258BF5FA4ABA" xtrim="148" ytrim="68" wtrim="108" htrim="412" xdraw="146" ydraw="66" wdraw="112" hdraw="416"/>
					<frame md5="8D13EDA71E49F59240C31A0E0838BC76" xtrim="148" ytrim="68" wtrim="108" htrim="412" xdraw="146" ydraw="66" wdraw="112" hdraw="416"/>
					<frame md5="4E5090D9B00447BF219991212FDF3980" xtrim="148" ytrim="68" wtrim="108" htrim="412" xdraw="146" ydraw="66" wdraw="112" hdraw="416"/>
					<frame md5="8D13EDA71E49F59240C31A0E0838BC76" xtrim="148" ytrim="68" wtrim="108" htrim="412" xdraw="146" ydraw="66" wdraw="112" hdraw="416"/>
					<frame md5="AD016F2A30E2A6898867BA65AF14D70B" xtrim="148" ytrim="68" wtrim="108" htrim="412" xdraw="146" ydraw="66" wdraw="112" hdraw="416"/>
					<frame md5="CA4D48A8525FE03B59ED27BF23ACCCEF" xtrim="148" ytrim="68" wtrim="108" htrim="412" xdraw="146" ydraw="66" wdraw="112" hdraw="416"/>
					<frame md5="AD016F2A30E2A6898867BA65AF14D70B" xtrim="148" ytrim="68" wtrim="108" htrim="412" xdraw="146" ydraw="66" wdraw="112" hdraw="416"/>
					<frame md5="8D13EDA71E49F59240C31A0E0838BC76" xtrim="148" ytrim="68" wtrim="108" htrim="412" xdraw="146" ydraw="66" wdraw="112" hdraw="416"/>
				</frames>
			</LEFT>
			<RIGHT count="41">
				<frames>
					<frame md5="8D13EDA71E49F59240C31A0E0838BC76" xtrim="144" ytrim="68" wtrim="108" htrim="412" xdraw="142" ydraw="66" wdraw="112" hdraw="416"/>
					<frame md5="27EF89757E8369808FDEE1260802EEBE" xtrim="148" ytrim="68" wtrim="104" htrim="412" xdraw="146" ydraw="66" wdraw="108" hdraw="416"/>
					<frame md5="05A81CE86725698D5D6B6AB9C8173E2F" xtrim="132" ytrim="68" wtrim="138" htrim="412" xdraw="130" ydraw="66" wdraw="142" hdraw="416"/>
					<frame md5="16B9EF650F4866408E77B7C15CE88B32" xtrim="104" ytrim="68" wtrim="186" htrim="412" xdraw="102" ydraw="66" wdraw="190" hdraw="416"/>
					<frame md5="D6BB796C887A55C361AC4E5663671473" xtrim="104" ytrim="68" wtrim="186" htrim="412" xdraw="102" ydraw="66" wdraw="190" hdraw="416"/>
					<frame md5="D6448E7575766FF9E3C3DB6A886ADF95" xtrim="104" ytrim="68" wtrim="186" htrim="412" xdraw="102" ydraw="66" wdraw="190" hdraw="416"/>
					<frame md5="526EA2BF7C5DB26D9F0E1D01C8C2A6C6" xtrim="104" ytrim="68" wtrim="186" htrim="412" xdraw="102" ydraw="66" wdraw="190" hdraw="416"/>
					<frame md5="D6BB796C887A55C361AC4E5663671473" xtrim="104" ytrim="68" wtrim="186" htrim="412" xdraw="102" ydraw="66" wdraw="190" hdraw="416"/>
					<frame md5="D6448E7575766FF9E3C3DB6A886ADF95" xtrim="104" ytrim="68" wtrim="186" htrim="412" xdraw="102" ydraw="66" wdraw="190" hdraw="416"/>
					<frame md5="D6BB796C887A55C361AC4E5663671473" xtrim="104" ytrim="68" wtrim="186" htrim="412" xdraw="102" ydraw="66" wdraw="190" hdraw="416"/>
					<frame md5="D6448E7575766FF9E3C3DB6A886ADF95" xtrim="104" ytrim="68" wtrim="186" htrim="412" xdraw="102" ydraw="66" wdraw="190" hdraw="416"/>
					<frame md5="05A81CE86725698D5D6B6AB9C8173E2F" xtrim="132" ytrim="68" wtrim="138" htrim="412" xdraw="130" ydraw="66" wdraw="142" hdraw="416"/>
					<frame md5="27EF89757E8369808FDEE1260802EEBE" xtrim="148" ytrim="68" wtrim="104" htrim="412" xdraw="146" ydraw="66" wdraw="108" hdraw="416"/>
					<frame md5="8D13EDA71E49F59240C31A0E0838BC76" xtrim="144" ytrim="68" wtrim="108" htrim="412" xdraw="142" ydraw="66" wdraw="112" hdraw="416"/>
					<frame md5="D51B073A4DEC710F04DA07E684DB5008" xtrim="144" ytrim="68" wtrim="108" htrim="412" xdraw="142" ydraw="66" wdraw="112" hdraw="416"/>
					<frame md5="8728AC82DE4B05729B0F3A242FC1AAB7" xtrim="144" ytrim="68" wtrim="108" htrim="412" xdraw="142" ydraw="66" wdraw="112" hdraw="416"/>
					<frame md5="8D13EDA71E49F59240C31A0E0838BC76" xtrim="144" ytrim="68" wtrim="108" htrim="412" xdraw="142" ydraw="66" wdraw="112" hdraw="416"/>
					<frame md5="4E5090D9B00447BF219991212FDF3980" xtrim="144" ytrim="68" wtrim="108" htrim="412" xdraw="142" ydraw="66" wdraw="112" hdraw="416"/>
					<frame md5="8D13EDA71E49F59240C31A0E0838BC76" xtrim="144" ytrim="68" wtrim="108" htrim="412" xdraw="142" ydraw="66" wdraw="112" hdraw="416"/>
					<frame md5="AD016F2A30E2A6898867BA65AF14D70B" xtrim="144" ytrim="68" wtrim="108" htrim="412" xdraw="142" ydraw="66" wdraw="112" hdraw="416"/>
					<frame md5="CA4D48A8525FE03B59ED27BF23ACCCEF" xtrim="144" ytrim="68" wtrim="108" htrim="412" xdraw="142" ydraw="66" wdraw="112" hdraw="416"/>
					<frame md5="AD016F2A30E2A6898867BA65AF14D70B" xtrim="144" ytrim="68" wtrim="108" htrim="412" xdraw="142" ydraw="66" wdraw="112" hdraw="416"/>
					<frame md5="8D13EDA71E49F59240C31A0E0838BC76" xtrim="144" ytrim="68" wtrim="108" htrim="412" xdraw="142" ydraw="66" wdraw="112" hdraw="416"/>
					<frame md5="6964CA9E4B4023D047D8258BF5FA4ABA" xtrim="144" ytrim="68" wtrim="108" htrim="412" xdraw="142" ydraw="66" wdraw="112" hdraw="416"/>
					<frame md5="F6DDD181A8883F48138DDEB471D0DCA5" xtrim="144" ytrim="68" wtrim="108" htrim="412" xdraw="142" ydraw="66" wdraw="112" hdraw="416"/>
					<frame md5="6A743A8A8384A1444B0C04D22607A1DC" xtrim="144" ytrim="68" wtrim="108" htrim="412" xdraw="142" ydraw="66" wdraw="112" hdraw="416"/>
					<frame md5="6A743A8A8384A1444B0C04D22607A1DC" xtrim="144" ytrim="68" wtrim="108" htrim="412" xdraw="142" ydraw="66" wdraw="112" hdraw="416"/>
					<frame md5="8F84193FC320BBE439F1690D2CBF5809" xtrim="144" ytrim="68" wtrim="108" htrim="412" xdraw="142" ydraw="66" wdraw="112" hdraw="416"/>
					<frame md5="4AC24399222983A54D5D1F2282CC79D1" xtrim="144" ytrim="68" wtrim="108" htrim="412" xdraw="142" ydraw="66" wdraw="112" hdraw="416"/>
					<frame md5="61E7EA63A035B60DA374E292F3FF1581" xtrim="144" ytrim="68" wtrim="108" htrim="412" xdraw="142" ydraw="66" wdraw="112" hdraw="416"/>
					<frame md5="5A20DD39F9E83683FC4CDD5179C72B04" xtrim="144" ytrim="68" wtrim="108" htrim="412" xdraw="142" ydraw="66" wdraw="112" hdraw="416"/>
					<frame md5="6E7B2091366501DE3EFE8097BFF64A38" xtrim="144" ytrim="68" wtrim="108" htrim="412" xdraw="142" ydraw="66" wdraw="112" hdraw="416"/>
					<frame md5="F6DDD181A8883F48138DDEB471D0DCA5" xtrim="144" ytrim="68" wtrim="108" htrim="412" xdraw="142" ydraw="66" wdraw="112" hdraw="416"/>
					<frame md5="6964CA9E4B4023D047D8258BF5FA4ABA" xtrim="144" ytrim="68" wtrim="108" htrim="412" xdraw="142" ydraw="66" wdraw="112" hdraw="416"/>
					<frame md5="8D13EDA71E49F59240C31A0E0838BC76" xtrim="144" ytrim="68" wtrim="108" htrim="412" xdraw="142" ydraw="66" wdraw="112" hdraw="416"/>
					<frame md5="4E5090D9B00447BF219991212FDF3980" xtrim="144" ytrim="68" wtrim="108" htrim="412" xdraw="142" ydraw="66" wdraw="112" hdraw="416"/>
					<frame md5="8D13EDA71E49F59240C31A0E0838BC76" xtrim="144" ytrim="68" wtrim="108" htrim="412" xdraw="142" ydraw="66" wdraw="112" hdraw="416"/>
					<frame md5="AD016F2A30E2A6898867BA65AF14D70B" xtrim="144" ytrim="68" wtrim="108" htrim="412" xdraw="142" ydraw="66" wdraw="112" hdraw="416"/>
					<frame md5="CA4D48A8525FE03B59ED27BF23ACCCEF" xtrim="144" ytrim="68" wtrim="108" htrim="412" xdraw="142" ydraw="66" wdraw="112" hdraw="416"/>
					<frame md5="AD016F2A30E2A6898867BA65AF14D70B" xtrim="144" ytrim="68" wtrim="108" htrim="412" xdraw="142" ydraw="66" wdraw="112" hdraw="416"/>
					<frame md5="8D13EDA71E49F59240C31A0E0838BC76" xtrim="144" ytrim="68" wtrim="108" htrim="412" xdraw="142" ydraw="66" wdraw="112" hdraw="416"/>
				</frames>
			</RIGHT>
			<FRONT>
				<frames/>
			</FRONT>
			<BACK>
				<frames/>
			</BACK>
		</SURPRISED_TALK>
	</anims>
	<events/>
	<packs>
		<frames>
			<frame pack="0" index="81" index2="-1" x="2" y="2" w="244" h="410"/>
			<frame pack="0" index="76" index2="-1" x="2" y="416" w="232" h="414"/>
			<frame pack="0" index="82" index2="-1" x="2" y="834" w="196" h="412"/>
			<frame pack="0" index="85" index2="-1" x="2" y="1250" w="192" h="406"/>
			<frame pack="0" index="77" index2="-1" x="250" y="2" w="184" h="418"/>
			<frame pack="0" index="179" index2="-1" x="438" y="2" w="186" h="412"/>
			<frame pack="0" index="180" index2="-1" x="628" y="2" w="186" h="412"/>
			<frame pack="0" index="181" index2="-1" x="818" y="2" w="186" h="412"/>
			<frame pack="0" index="182" index2="-1" x="1008" y="2" w="186" h="412"/>
			<frame pack="0" index="80" index2="-1" x="1198" y="2" w="170" h="408"/>
			<frame pack="0" index="112" index2="-1" x="2" y="1660" w="170" h="368"/>
			<frame pack="0" index="83" index2="-1" x="1372" y="2" w="424" h="140" rotated="1"/>
			<frame pack="0" index="111" index2="-1" x="1372" y="146" w="398" h="146" rotated="1"/>
			<frame pack="0" index="178" index2="-1" x="250" y="424" w="138" h="412"/>
			<frame pack="0" index="84" index2="-1" x="250" y="840" w="120" h="418"/>
			<frame pack="0" index="126" index2="-1" x="250" y="1262" w="114" h="434"/>
			<frame pack="0" index="121" index2="-1" x="392" y="424" w="114" h="434"/>
			<frame pack="0" index="120" index2="-1" x="392" y="862" w="114" h="432"/>
			<frame pack="0" index="79" index2="-1" x="510" y="424" w="118" h="416"/>
			<frame pack="0" index="122" index2="-1" x="392" y="1298" w="112" h="434"/>
			<frame pack="0" index="123" index2="-1" x="510" y="844" w="112" h="434"/>
			<frame pack="0" index="115" index2="-1" x="1774" y="146" w="210" h="230"/>
			<frame pack="0" index="114" index2="-1" x="632" y="424" w="208" h="232"/>
			<frame pack="0" index="116" index2="-1" x="844" y="424" w="208" h="230"/>
			<frame pack="0" index="78" index2="-1" x="510" y="1282" w="112" h="422"/>
			<frame pack="0" index="107" index2="-1" x="1056" y="424" w="436" h="106" rotated="1"/>
			<frame pack="0" index="117" index2="-1" x="1496" y="424" w="250" h="186" rotated="1"/>
			<frame pack="0" index="108" index2="-1" x="1056" y="534" w="432" h="106" rotated="1"/>
			<frame pack="0" index="104" index2="-1" x="632" y="660" w="106" h="430"/>
			<frame pack="0" index="101" index2="-1" x="632" y="1094" w="102" h="444"/>
			<frame pack="0" index="103" index2="-1" x="632" y="1542" w="104" h="432"/>
			<frame pack="0" index="113" index2="-1" x="1750" y="424" w="266" h="170" rotated="1"/>
			<frame pack="0" index="146" index2="-1" x="742" y="660" w="108" h="414"/>
			<frame pack="0" index="145" index2="-1" x="742" y="1078" w="108" h="414"/>
			<frame pack="0" index="0" index2="-1" x="742" y="1496" w="108" h="414"/>
			<frame pack="0" index="196" index2="-1" x="854" y="660" w="108" h="412"/>
			<frame pack="0" index="199" index2="-1" x="854" y="1076" w="108" h="412"/>
			<frame pack="0" index="200" index2="-1" x="854" y="1492" w="108" h="412"/>
			<frame pack="0" index="4" index2="-1" x="966" y="660" w="108" h="412"/>
			<frame pack="0" index="5" index2="-1" x="1078" y="660" w="108" h="412"/>
			<frame pack="0" index="6" index2="-1" x="1190" y="660" w="108" h="412"/>
			<frame pack="0" index="201" index2="-1" x="1302" y="660" w="108" h="412"/>
			<frame pack="0" index="203" index2="-1" x="1414" y="660" w="108" h="412"/>
			<frame pack="0" index="204" index2="-1" x="1526" y="660" w="108" h="412"/>
			<frame pack="0" index="205" index2="-1" x="1638" y="660" w="108" h="412"/>
			<frame pack="0" index="206" index2="-1" x="1750" y="660" w="108" h="412"/>
			<frame pack="0" index="207" index2="-1" x="1862" y="660" w="108" h="412"/>
			<frame pack="0" index="149" index2="-1" x="966" y="1076" w="108" h="412"/>
			<frame pack="0" index="150" index2="-1" x="966" y="1492" w="108" h="412"/>
			<frame pack="0" index="191" index2="-1" x="1078" y="1076" w="108" h="412"/>
			<frame pack="0" index="157" index2="-1" x="1078" y="1492" w="108" h="412"/>
			<frame pack="0" index="158" index2="-1" x="1190" y="1076" w="108" h="412"/>
			<frame pack="0" index="176" index2="-1" x="1190" y="1492" w="108" h="412"/>
			<frame pack="0" index="190" index2="-1" x="1302" y="1076" w="108" h="412"/>
			<frame pack="0" index="193" index2="-1" x="1302" y="1492" w="108" h="412"/>
			<frame pack="0" index="195" index2="-1" x="1414" y="1076" w="108" h="412"/>
			<frame pack="0" index="100" index2="-1" x="1526" y="1076" w="452" h="98" rotated="1"/>
			<frame pack="0" index="105" index2="-1" x="1526" y="1178" w="426" h="104" rotated="1"/>
			<frame pack="0" index="152" index2="-1" x="1526" y="1286" w="410" h="108" rotated="1"/>
			<frame pack="0" index="7" index2="-1" x="1414" y="1492" w="108" h="410"/>
			<frame pack="0" index="8" index2="-1" x="1526" y="1492" w="108" h="410"/>
			<frame pack="0" index="110" index2="-1" x="1638" y="1492" w="102" h="432"/>
			<frame pack="0" index="125" index2="-1" x="1744" y="1492" w="102" h="432"/>
			<frame pack="0" index="9" index2="-1" x="1850" y="1492" w="108" h="408"/>
			<frame pack="0" index="118" index2="-1" x="250" y="1700" w="130" h="328"/>
			<frame pack="0" index="119" index2="-1" x="1372" y="296" w="392" h="106" rotated="1"/>
			<frame pack="0" index="38" index2="34"/>
			<frame pack="0" index="39" index2="32"/>
			<frame pack="0" index="40" index2="32"/>
			<frame pack="0" index="41" index2="32"/>
			<frame pack="0" index="44" index2="42"/>
			<frame pack="0" index="45" index2="32"/>
			<frame pack="0" index="46" index2="32"/>
			<frame pack="0" index="47" index2="32"/>
			<frame pack="0" index="48" index2="32"/>
			<frame pack="0" index="54" index2="52"/>
			<frame pack="0" index="55" index2="51"/>
			<frame pack="0" index="56" index2="53"/>
			<frame pack="0" index="57" index2="52"/>
			<frame pack="0" index="58" index2="51"/>
			<frame pack="0" index="59" index2="50"/>
			<frame pack="0" index="60" index2="49"/>
			<frame pack="0" index="62" index2="61"/>
			<frame pack="0" index="63" index2="61"/>
			<frame pack="0" index="64" index2="61"/>
			<frame pack="0" index="70" index2="69"/>
			<frame pack="0" index="71" index2="69"/>
			<frame pack="0" index="72" index2="68"/>
			<frame pack="0" index="73" index2="67"/>
			<frame pack="0" index="74" index2="66"/>
			<frame pack="0" index="75" index2="65"/>
			<frame pack="0" index="86" index2="76" flipped="1"/>
			<frame pack="0" index="87" index2="77" flipped="1"/>
			<frame pack="0" index="88" index2="78" flipped="1"/>
			<frame pack="0" index="89" index2="79" flipped="1"/>
			<frame pack="0" index="90" index2="80" flipped="1"/>
			<frame pack="0" index="91" index2="81" flipped="1"/>
			<frame pack="0" index="92" index2="82" flipped="1"/>
			<frame pack="0" index="93" index2="83" flipped="1"/>
			<frame pack="0" index="94" index2="84" flipped="1"/>
			<frame pack="0" index="95" index2="85" flipped="1"/>
			<frame pack="0" index="127" index2="110" flipped="1"/>
			<frame pack="0" index="128" index2="111" flipped="1"/>
			<frame pack="0" index="129" index2="112" flipped="1"/>
			<frame pack="0" index="130" index2="113" flipped="1"/>
			<frame pack="0" index="131" index2="114" flipped="1"/>
			<frame pack="0" index="132" index2="115" flipped="1"/>
			<frame pack="0" index="133" index2="116" flipped="1"/>
			<frame pack="0" index="134" index2="117" flipped="1"/>
			<frame pack="0" index="135" index2="118" flipped="1"/>
			<frame pack="0" index="136" index2="119" flipped="1"/>
			<frame pack="0" index="137" index2="120" flipped="1"/>
			<frame pack="0" index="138" index2="121" flipped="1"/>
			<frame pack="0" index="139" index2="122" flipped="1"/>
			<frame pack="0" index="140" index2="123" flipped="1"/>
			<frame pack="0" index="141" index2="124" flipped="1"/>
			<frame pack="0" index="142" index2="125" flipped="1"/>
			<frame pack="0" index="143" index2="126" flipped="1"/>
			<frame pack="0" index="144" index2="0"/>
			<frame pack="0" index="1" index2="0"/>
			<frame pack="0" index="2" index2="0"/>
			<frame pack="0" index="147" index2="0"/>
			<frame pack="0" index="148" index2="0"/>
			<frame pack="0" index="3" index2="0"/>
			<frame pack="0" index="10" index2="9"/>
			<frame pack="0" index="151" index2="6"/>
			<frame pack="0" index="11" index2="8"/>
			<frame pack="0" index="153" index2="8"/>
			<frame pack="0" index="154" index2="9"/>
			<frame pack="0" index="155" index2="8"/>
			<frame pack="0" index="156" index2="7"/>
			<frame pack="0" index="12" index2="7"/>
			<frame pack="0" index="13" index2="6"/>
			<frame pack="0" index="159" index2="4"/>
			<frame pack="0" index="160" index2="0" flipped="1"/>
			<frame pack="0" index="161" index2="145" flipped="1"/>
			<frame pack="0" index="162" index2="146" flipped="1"/>
			<frame pack="0" index="163" index2="0" flipped="1"/>
			<frame pack="0" index="164" index2="0" flipped="1"/>
			<frame pack="0" index="165" index2="149" flipped="1"/>
			<frame pack="0" index="166" index2="150" flipped="1"/>
			<frame pack="0" index="167" index2="6" flipped="1"/>
			<frame pack="0" index="168" index2="152" flipped="1"/>
			<frame pack="0" index="169" index2="8" flipped="1"/>
			<frame pack="0" index="170" index2="9" flipped="1"/>
			<frame pack="0" index="171" index2="8" flipped="1"/>
			<frame pack="0" index="172" index2="7" flipped="1"/>
			<frame pack="0" index="173" index2="157" flipped="1"/>
			<frame pack="0" index="174" index2="158" flipped="1"/>
			<frame pack="0" index="175" index2="4" flipped="1"/>
			<frame pack="0" index="14" index2="5"/>
			<frame pack="0" index="15" index2="4"/>
			<frame pack="0" index="16" index2="0" flipped="1"/>
			<frame pack="0" index="17" index2="0" flipped="1"/>
			<frame pack="0" index="18" index2="0" flipped="1"/>
			<frame pack="0" index="19" index2="0" flipped="1"/>
			<frame pack="0" index="20" index2="4" flipped="1"/>
			<frame pack="0" index="183" index2="180"/>
			<frame pack="0" index="184" index2="181"/>
			<frame pack="0" index="185" index2="180"/>
			<frame pack="0" index="186" index2="181"/>
			<frame pack="0" index="187" index2="178"/>
			<frame pack="0" index="188" index2="177"/>
			<frame pack="0" index="189" index2="176"/>
			<frame pack="0" index="21" index2="5" flipped="1"/>
			<frame pack="0" index="22" index2="6" flipped="1"/>
			<frame pack="0" index="192" index2="176"/>
			<frame pack="0" index="23" index2="7" flipped="1"/>
			<frame pack="0" index="194" index2="176"/>
			<frame pack="0" index="24" index2="8" flipped="1"/>
			<frame pack="0" index="25" index2="9" flipped="1"/>
			<frame pack="0" index="197" index2="195"/>
			<frame pack="0" index="198" index2="176"/>
			<frame pack="0" index="26" index2="9" flipped="1"/>
			<frame pack="0" index="27" index2="8" flipped="1"/>
			<frame pack="0" index="28" index2="7" flipped="1"/>
			<frame pack="0" index="202" index2="201"/>
			<frame pack="0" index="29" index2="6" flipped="1"/>
			<frame pack="0" index="30" index2="5" flipped="1"/>
			<frame pack="0" index="31" index2="4" flipped="1"/>
			<frame pack="0" index="33" index2="32"/>
			<frame pack="0" index="37" index2="35"/>
			<frame pack="0" index="208" index2="200"/>
			<frame pack="0" index="209" index2="199"/>
			<frame pack="0" index="210" index2="176"/>
			<frame pack="0" index="211" index2="193"/>
			<frame pack="0" index="212" index2="176"/>
			<frame pack="0" index="213" index2="195"/>
			<frame pack="0" index="214" index2="196"/>
			<frame pack="0" index="215" index2="195"/>
			<frame pack="0" index="216" index2="176"/>
			<frame pack="0" index="217" index2="176" flipped="1"/>
			<frame pack="0" index="218" index2="177" flipped="1"/>
			<frame pack="0" index="219" index2="178" flipped="1"/>
			<frame pack="0" index="220" index2="179" flipped="1"/>
			<frame pack="0" index="221" index2="180" flipped="1"/>
			<frame pack="0" index="222" index2="181" flipped="1"/>
			<frame pack="0" index="223" index2="182" flipped="1"/>
			<frame pack="0" index="224" index2="180" flipped="1"/>
			<frame pack="0" index="225" index2="181" flipped="1"/>
			<frame pack="0" index="226" index2="180" flipped="1"/>
			<frame pack="0" index="227" index2="181" flipped="1"/>
			<frame pack="0" index="228" index2="178" flipped="1"/>
			<frame pack="0" index="229" index2="177" flipped="1"/>
			<frame pack="0" index="230" index2="176" flipped="1"/>
			<frame pack="0" index="231" index2="190" flipped="1"/>
			<frame pack="0" index="232" index2="191" flipped="1"/>
			<frame pack="0" index="233" index2="176" flipped="1"/>
			<frame pack="0" index="234" index2="193" flipped="1"/>
			<frame pack="0" index="235" index2="176" flipped="1"/>
			<frame pack="0" index="236" index2="195" flipped="1"/>
			<frame pack="0" index="237" index2="196" flipped="1"/>
			<frame pack="0" index="238" index2="195" flipped="1"/>
			<frame pack="0" index="239" index2="176" flipped="1"/>
			<frame pack="0" index="240" index2="199" flipped="1"/>
			<frame pack="0" index="241" index2="200" flipped="1"/>
			<frame pack="0" index="242" index2="201" flipped="1"/>
			<frame pack="0" index="243" index2="201" flipped="1"/>
			<frame pack="0" index="244" index2="203" flipped="1"/>
			<frame pack="0" index="245" index2="204" flipped="1"/>
			<frame pack="0" index="246" index2="205" flipped="1"/>
			<frame pack="0" index="247" index2="206" flipped="1"/>
			<frame pack="0" index="248" index2="207" flipped="1"/>
			<frame pack="0" index="249" index2="200" flipped="1"/>
			<frame pack="0" index="250" index2="199" flipped="1"/>
			<frame pack="0" index="251" index2="176" flipped="1"/>
			<frame pack="0" index="252" index2="193" flipped="1"/>
			<frame pack="0" index="253" index2="176" flipped="1"/>
			<frame pack="0" index="254" index2="195" flipped="1"/>
			<frame pack="0" index="255" index2="196" flipped="1"/>
			<frame pack="0" index="256" index2="195" flipped="1"/>
			<frame pack="0" index="257" index2="176" flipped="1"/>
			<frame pack="1" index="124" index2="-1" x="2" y="2" w="100" h="432"/>
			<frame pack="1" index="102" index2="-1" x="2" y="438" w="98" h="430"/>
			<frame pack="1" index="96" index2="-1" x="106" y="2" w="102" h="426"/>
			<frame pack="1" index="98" index2="-1" x="106" y="432" w="100" h="422"/>
			<frame pack="1" index="97" index2="-1" x="212" y="2" w="98" h="422"/>
			<frame pack="1" index="32" index2="-1" x="314" y="2" w="100" h="420"/>
			<frame pack="1" index="49" index2="-1" x="314" y="426" w="100" h="420"/>
			<frame pack="1" index="34" index2="-1" x="418" y="2" w="100" h="420"/>
			<frame pack="1" index="42" index2="-1" x="522" y="2" w="100" h="420"/>
			<frame pack="1" index="50" index2="-1" x="626" y="2" w="100" h="418"/>
			<frame pack="1" index="35" index2="-1" x="730" y="2" w="100" h="418"/>
			<frame pack="1" index="43" index2="-1" x="834" y="2" w="100" h="418"/>
			<frame pack="1" index="99" index2="-1" x="938" y="2" w="102" h="416"/>
			<frame pack="1" index="109" index2="-1" x="1044" y="2" w="102" h="416"/>
			<frame pack="1" index="36" index2="-1" x="418" y="426" w="100" h="416"/>
			<frame pack="1" index="51" index2="-1" x="522" y="426" w="100" h="416"/>
			<frame pack="1" index="52" index2="-1" x="626" y="426" w="100" h="414"/>
			<frame pack="1" index="53" index2="-1" x="730" y="426" w="100" h="414"/>
			<frame pack="1" index="106" index2="-1" x="834" y="426" w="106" h="412"/>
			<frame pack="1" index="177" index2="-1" x="944" y="426" w="104" h="412"/>
			<frame pack="1" index="61" index2="-1" x="212" y="428" w="96" h="396"/>
			<frame pack="1" index="65" index2="-1" x="212" y="828" w="96" h="396"/>
			<frame pack="1" index="66" index2="-1" x="1052" y="426" w="96" h="394"/>
			<frame pack="1" index="69" index2="-1" x="834" y="842" w="394" h="94" rotated="1"/>
			<frame pack="1" index="68" index2="-1" x="834" y="940" w="394" h="94" rotated="1"/>
			<frame pack="1" index="67" index2="-1" x="834" y="1038" w="394" h="94" rotated="1"/>
		</frames>
		<packs>
			<pack count="232" groupType="0"/>
			<pack count="26" groupType="0"/>
		</packs>
	</packs>
	<subs/>
</xml>
